binance/__init__.py
binance/pay/__init__.py
binance/pay/__version__.py
binance/pay/api.py
binance/pay/error.py
binance/pay/merchant.py
binance/pay/lib/__init__.py
binance/pay/lib/utils.py
tests/pay/__init__.py
tests/pay/test_util.py
binance_pay_connector-1.0.0.dist-info/LICENSE.md
binance_pay_connector-1.0.0.dist-info/METADATA
binance_pay_connector-1.0.0.dist-info/WHEEL
binance_pay_connector-1.0.0.dist-info/top_level.txt
binance_pay_connector-1.0.0.dist-info/RECORD
