Metadata-Version: 2.1
Name: binance-pay-connector
Version: 1.0.0
Summary: This is a lightweight library that works as a connector to Binance Pay public API
Home-page: https://github.com/binance/binance-pay-connector-python
License: MIT
Keywords: Binance,Binance Pay,Public API
Platform: UNKNOWN
Classifier: Intended Audience :: Developers
Classifier: Intended Audience :: Financial and Insurance Industry
Classifier: License :: OSI Approved :: MIT License
Classifier: Programming Language :: Python :: 3.6
Classifier: Programming Language :: Python :: 3.7
Classifier: Programming Language :: Python :: 3.8
Classifier: Programming Language :: Python :: 3.9
Classifier: Programming Language :: Python :: 3.10
Requires-Python: >=3.6
